talos_contracts/__init__.py
talos_contracts/base64url.py
talos_contracts/cursor.py
talos_contracts/ordering.py
talos_contracts/py.typed
talos_contracts/uuidv7.py
talos_contracts/domain/__init__.py
talos_contracts/domain/logic/__init__.py
talos_contracts/domain/logic/cursor.py
talos_contracts/domain/logic/ordering.py
talos_contracts/domain/types/__init__.py
talos_contracts/domain/types/cursor_types.py
talos_contracts/infrastructure/__init__.py
talos_contracts/infrastructure/base64url.py
talos_contracts/infrastructure/uuidv7.py
talos_contracts-1.1.15.dist-info/METADATA
talos_contracts-1.1.15.dist-info/WHEEL
talos_contracts-1.1.15.dist-info/top_level.txt
talos_contracts-1.1.15.dist-info/RECORD
