Metadata-Version: 2.4
Name: talos-contracts
Version: 1.1.15
Summary: Talos Protocol contracts - schemas, types, and helper functions for auditable AI agent security
Author: Talos Protocol
License: MIT
Project-URL: Homepage, https://github.com/talosprotocol/talos-contracts
Project-URL: Repository, https://github.com/talosprotocol/talos-contracts
Project-URL: Documentation, https://github.com/talosprotocol/talos-contracts#readme
Keywords: talos,protocol,contracts,mcp,security,audit,ai-agent
Requires-Python: >=3.10
Provides-Extra: dev
Requires-Dist: pytest>=7.0.0; extra == "dev"
Requires-Dist: pytest-cov>=4.0.0; extra == "dev"
Requires-Dist: pytest-asyncio>=0.21.0; extra == "dev"
Requires-Dist: mypy>=1.0.0; extra == "dev"
Requires-Dist: ruff>=0.1.0; extra == "dev"
